streamlit_multipage/__init__.py
streamlit_multipage/multipage.py
streamlit_multipage-0.0.17.dist-info/LICENSE
streamlit_multipage-0.0.17.dist-info/METADATA
streamlit_multipage-0.0.17.dist-info/WHEEL
streamlit_multipage-0.0.17.dist-info/top_level.txt
streamlit_multipage-0.0.17.dist-info/RECORD
