Metadata-Version: 2.1
Name: streamlit-multipage
Version: 0.0.17
Summary: A small package that allows you to create multi page streamlit apps
Home-page: https://github.com/ELC/streamlit-multipage
Author: Yan Almeida, Ezequiel Leonardo Castaño
Author-email: author@example.com
License: UNKNOWN
Project-URL: Bug Tracker, https://github.com/ELC/streamlit-multipage/issues
Platform: UNKNOWN
Classifier: Programming Language :: Python :: 3
Classifier: Operating System :: OS Independent
Requires-Python: >=3.6
License-File: LICENSE
